thonnycontrib/thonny-physicum-image.py
thonny_physicum_rooftop-1.1.1.dist-info/LICENSE
thonny_physicum_rooftop-1.1.1.dist-info/METADATA
thonny_physicum_rooftop-1.1.1.dist-info/WHEEL
thonny_physicum_rooftop-1.1.1.dist-info/top_level.txt
thonny_physicum_rooftop-1.1.1.dist-info/RECORD
